rebound/__init__.py
rebound/__main__.py
rebound/rebound.py
rebound_cli-1.1.6a1.dist-info/DESCRIPTION.rst
rebound_cli-1.1.6a1.dist-info/METADATA
rebound_cli-1.1.6a1.dist-info/RECORD
rebound_cli-1.1.6a1.dist-info/WHEEL
rebound_cli-1.1.6a1.dist-info/entry_points.txt
rebound_cli-1.1.6a1.dist-info/metadata.json
rebound_cli-1.1.6a1.dist-info/top_level.txt
