Metadata-Version: 2.0
Name: rebound-cli
Version: 1.1.6a1
Summary: Automatically displays Stack Overflow results when you get a compiler error
Home-page: https://github.com/shobrook/rebound
Author: shobrook
Author-email: shobrookj@gmail.com
License: MIT
Keywords: stackoverflow stack overflow debug debugging error-handling compile errors error message cli
Platform: UNKNOWN
Classifier: Development Status :: 3 - Alpha
Classifier: Environment :: Console
Classifier: Intended Audience :: Developers
Classifier: Topic :: Software Development
Classifier: Topic :: Software Development :: Debuggers
Classifier: Natural Language :: English
Classifier: License :: OSI Approved :: MIT License
Classifier: Programming Language :: Python
Requires: BeautifulSoup4
Requires: requests
Requires: urllib3
Requires: urwid
Requires-Python: >=3
Requires-Dist: BeautifulSoup4
Requires-Dist: requests
Requires-Dist: urllib3
Requires-Dist: urwid
